weakl/__init__.py
weakl/adaptive.py
weakl/additive_model.py
weakl/hierarchical.py
weakl/utils.py
weakl-0.0.6.dist-info/METADATA
weakl-0.0.6.dist-info/WHEEL
weakl-0.0.6.dist-info/licenses/LICENSE
weakl-0.0.6.dist-info/RECORD
