Metadata-Version: 2.4
Name: weakl
Version: 0.0.6
Summary: A package implementing kernel methods with weak physics for time series
Project-URL: Homepage, https://github.com/NathanDoumeche/weakl
Project-URL: Issues, https://github.com/NathanDoumeche/weakl/issues
Author-email: Nathan Doumèche <nathan.doumeche@gmail.com>
License-Expression: MIT
License-File: LICENSE
Classifier: Operating System :: OS Independent
Classifier: Programming Language :: Python :: 3
Requires-Python: >=3.9
Requires-Dist: matplotlib>=3.9.0
Requires-Dist: numpy>=2.0.0
Requires-Dist: pandas>=2.2.2
Requires-Dist: torch>=2.4.1
